alibi/__init__.py
alibi/exceptions.py
alibi/saving.py
alibi/version.py
alibi/api/__init__.py
alibi/api/defaults.py
alibi/api/interfaces.py
alibi/api/tests/__init__.py
alibi/api/tests/test_interfaces.py
alibi/confidence/__init__.py
alibi/confidence/model_linearity.py
alibi/confidence/trustscore.py
alibi/confidence/tests/__init__.py
alibi/confidence/tests/test_model_linearity.py
alibi/confidence/tests/test_trustscore.py
alibi/data/cats.tar.gz
alibi/datasets/__init__.py
alibi/datasets/default.py
alibi/datasets/tensorflow.py
alibi/datasets/tests/__init__.py
alibi/datasets/tests/test_datasets.py
alibi/explainers/__init__.py
alibi/explainers/ale.py
alibi/explainers/cem.py
alibi/explainers/cfproto.py
alibi/explainers/cfrl_base.py
alibi/explainers/cfrl_tabular.py
alibi/explainers/counterfactual.py
alibi/explainers/integrated_gradients.py
alibi/explainers/partial_dependence.py
alibi/explainers/pd_variance.py
alibi/explainers/permutation_importance.py
alibi/explainers/shap_wrappers.py
alibi/explainers/anchors/__init__.py
alibi/explainers/anchors/anchor_base.py
alibi/explainers/anchors/anchor_explanation.py
alibi/explainers/anchors/anchor_image.py
alibi/explainers/anchors/anchor_tabular.py
alibi/explainers/anchors/anchor_tabular_distributed.py
alibi/explainers/anchors/anchor_text.py
alibi/explainers/anchors/language_model_text_sampler.py
alibi/explainers/anchors/text_samplers.py
alibi/explainers/backends/__init__.py
alibi/explainers/backends/cfrl_base.py
alibi/explainers/backends/cfrl_tabular.py
alibi/explainers/backends/pytorch/__init__.py
alibi/explainers/backends/pytorch/cfrl_base.py
alibi/explainers/backends/pytorch/cfrl_tabular.py
alibi/explainers/backends/tensorflow/__init__.py
alibi/explainers/backends/tensorflow/cfrl_base.py
alibi/explainers/backends/tensorflow/cfrl_tabular.py
alibi/explainers/similarity/__init__.py
alibi/explainers/similarity/base.py
alibi/explainers/similarity/grad.py
alibi/explainers/similarity/metrics.py
alibi-0.9.6.dist-info/LICENSE
alibi-0.9.6.dist-info/METADATA
alibi-0.9.6.dist-info/WHEEL
alibi-0.9.6.dist-info/top_level.txt
alibi-0.9.6.dist-info/RECORD
