Metadata-Version: 2.1
Name: alibi
Version: 0.9.6
Summary: Algorithms for monitoring and explaining machine learning models
Home-page: https://github.com/SeldonIO/alibi
Author: Seldon Technologies Ltd.
Author-email: hello@seldon.io
License: Business Source License 1.1
Classifier: Intended Audience :: Science/Research
Classifier: Operating System :: OS Independent
Classifier: Programming Language :: Python :: 3
Classifier: Programming Language :: Python :: 3.8
Classifier: Programming Language :: Python :: 3.9
Classifier: Programming Language :: Python :: 3.10
Classifier: Programming Language :: Python :: 3.11
Classifier: License :: Other/Proprietary License
Classifier: Topic :: Scientific/Engineering
Requires-Python: >=3.8
License-File: LICENSE
Requires-Dist: numpy<2.0.0,>=1.16.2
Requires-Dist: pandas<3.0.0,>=1.0.0
Requires-Dist: scikit-learn<2.0.0,>=1.0.0
Requires-Dist: spacy[lookups]<4.0.0,>=2.0.0
Requires-Dist: blis<0.8.0
Requires-Dist: scikit-image<0.23,>=0.17.2
Requires-Dist: requests<3.0.0,>=2.21.0
Requires-Dist: Pillow<11.0,>=5.4.1
Requires-Dist: attrs<24.0.0,>=19.2.0
Requires-Dist: scipy<2.0.0,>=1.1.0
Requires-Dist: matplotlib<4.0.0,>=3.0.0
Requires-Dist: typing-extensions>=3.7.4.3
Requires-Dist: dill<0.4.0,>=0.3.0
Requires-Dist: transformers<5.0.0,>=4.7.0
Requires-Dist: tqdm<5.0.0,>=4.28.1
Provides-Extra: ray
Requires-Dist: ray<3.0.0,>=0.8.7; extra == "ray"
Provides-Extra: shap
Requires-Dist: shap<0.44.0,>=0.40.0; extra == "shap"
Requires-Dist: numba!=0.54.0,<0.60.0,>=0.50.0; extra == "shap"
Provides-Extra: tensorflow
Requires-Dist: tensorflow!=2.6.0,!=2.6.1,<2.15.0,>=2.0.0; extra == "tensorflow"
Provides-Extra: torch
Requires-Dist: torch<3.0.0,>=1.9.0; extra == "torch"
Provides-Extra: all
Requires-Dist: ray<3.0.0,>=0.8.7; extra == "all"
Requires-Dist: shap<0.44.0,>=0.40.0; extra == "all"
Requires-Dist: numba!=0.54.0,<0.60.0,>=0.50.0; extra == "all"
Requires-Dist: tensorflow!=2.6.0,!=2.6.1,<2.15.0,>=2.0.0; extra == "all"
Requires-Dist: torch<3.0.0,>=1.9.0; extra == "all"
